mail_guesser/__init__.py
mail_guesser-0.0.2.dist-info/METADATA
mail_guesser-0.0.2.dist-info/WHEEL
mail_guesser-0.0.2.dist-info/top_level.txt
mail_guesser-0.0.2.dist-info/RECORD
