Metadata-Version: 2.1
Name: mail-guesser
Version: 0.0.2
Summary: A Email Guesser
Home-page: https://github.com/snifhex/email-guesser
Author: Sachin Tripathi
Author-email: sachintripathi@protonmail.com
License: UNKNOWN
Platform: UNKNOWN
Classifier: Programming Language :: Python :: 3
Classifier: License :: OSI Approved :: MIT License
Classifier: Operating System :: OS Independent
Requires-Python: >=3.6
